piidigger/__init__.py
piidigger/__main__.py
piidigger/classes.py
piidigger/console.py
piidigger/filescan.py
piidigger/getencoding.py
piidigger/getmime.py
piidigger/globalfuncs.py
piidigger/globalvars.py
piidigger/logmanager.py
piidigger/piidigger.py
piidigger/queuefuncs.py
piidigger/datahandlers/__init__.py
piidigger/datahandlers/email.py
piidigger/datahandlers/emailaddr.py
piidigger/datahandlers/pan.py
piidigger/datahandlers/phonenum.py
piidigger/datahandlers/trackdata.py
piidigger/filehandlers/__init__.py
piidigger/filehandlers/_sharedfuncs.py
piidigger/filehandlers/docx.py
piidigger/filehandlers/pdf.py
piidigger/filehandlers/plaintext.py
piidigger/filehandlers/xls.py
piidigger/filehandlers/xlsx.py
piidigger/outputhandlers/__init__.py
piidigger/outputhandlers/csv.py
piidigger/outputhandlers/json.py
piidigger/outputhandlers/text.py
piidigger-1.2.0.dist-info/licenses/LICENSE
piidigger-1.2.0.dist-info/METADATA
piidigger-1.2.0.dist-info/WHEEL
piidigger-1.2.0.dist-info/entry_points.txt
piidigger-1.2.0.dist-info/top_level.txt
piidigger-1.2.0.dist-info/RECORD
