Metadata-Version: 2.4
Name: piidigger
Version: 1.2.0
Summary: Python program to identify Personally Identifiable Information in common file types
Author-email: Randy Bartels <rjbartels@outlook.com>
Project-URL: Homepage, https://github.com/kirkpatrickprice/PIIDigger
Project-URL: Issues, https://github.com/kirkpatrickprice/PIIDigger/issues
Keywords: pii discovery,data discovery,credit card discovery
Classifier: Development Status :: 4 - Beta
Classifier: Intended Audience :: Information Technology
Classifier: Intended Audience :: System Administrators
Classifier: License :: OSI Approved :: Apache Software License
Classifier: Operating System :: OS Independent
Classifier: Programming Language :: Python :: 3
Classifier: Topic :: Security
Classifier: Topic :: Utilities
Requires-Python: <4,>=3.9
License-File: LICENSE
Requires-Dist: chardet==5.2.0
Requires-Dist: colorama==0.4.6
Requires-Dist: docx2python==2.10.1
Requires-Dist: openpyxl==3.0.10
Requires-Dist: puremagic==1.20
Requires-Dist: pypdf==5.4.0
Requires-Dist: pyyaml==6.0.1
Requires-Dist: tomli==2.0.1
Requires-Dist: wakepy==0.7.2
Requires-Dist: xlrd==2.0.1
Provides-Extra: dev
Requires-Dist: pytest>=7.4.4; extra == "dev"
Provides-Extra: test
Requires-Dist: pytest>=7.4.4; extra == "test"
Provides-Extra: win
Requires-Dist: pywin32; extra == "win"
Provides-Extra: build
Requires-Dist: pyinstaller>=6.6.0; extra == "build"
Provides-Extra: pypi
Requires-Dist: build>=1.2.1; extra == "pypi"
Requires-Dist: twine>=5.0.0; extra == "pypi"
Dynamic: license-file
